pylangacq/__init__.py
pylangacq/_clean_utterance.py
pylangacq/_punctuation_marks.py
pylangacq/chat.py
pylangacq/dependency.py
pylangacq/measures.py
pylangacq/objects.py
pylangacq/tests/README.md
pylangacq/tests/__init__.py
pylangacq/tests/eve.cha
pylangacq/tests/test_chat.py
pylangacq-0.19.1.dist-info/LICENSE.txt
pylangacq-0.19.1.dist-info/METADATA
pylangacq-0.19.1.dist-info/WHEEL
pylangacq-0.19.1.dist-info/top_level.txt
pylangacq-0.19.1.dist-info/RECORD
